{
  "build": "cpu_pyhb8f9a19_2",
  "build_number": 2,
  "channel": "https://conda.anaconda.org/conda-forge/noarch",
  "constrains": [],
  "depends": [
    "py-xgboost 2.1.1 cpu_pyhb442362_2",
    "python >=3.8"
  ],
  "extracted_package_dir": "C:\\Users\\vikas\\anaconda3\\pkgs\\xgboost-2.1.1-cpu_pyhb8f9a19_2",
  "files": [],
  "fn": "xgboost-2.1.1-cpu_pyhb8f9a19_2.conda",
  "license": "Apache-2.0",
  "link": {
    "source": "C:\\Users\\vikas\\anaconda3\\pkgs\\xgboost-2.1.1-cpu_pyhb8f9a19_2",
    "type": 1
  },
  "md5": "fe19244eb25a2c511e2f2233a1a41ea3",
  "name": "xgboost",
  "noarch": "python",
  "package_tarball_full_path": "C:\\Users\\vikas\\anaconda3\\pkgs\\xgboost-2.1.1-cpu_pyhb8f9a19_2.conda",
  "package_type": "noarch_python",
  "paths_data": {
    "paths": [],
    "paths_version": 1
  },
  "requested_spec": "xgboost",
  "sha256": "a1f44e74bfe43967fe00b454b507acc335adc31300bd0d5dff9a43fb3ac49f85",
  "size": 15307,
  "subdir": "noarch",
  "timestamp": 1724808863000,
  "url": "https://conda.anaconda.org/conda-forge/noarch/xgboost-2.1.1-cpu_pyhb8f9a19_2.conda",
  "version": "2.1.1"
}